poopmap_api/__init__.py
poopmap_api/poopmap_api.py
poopmap_api-0.0.2.dist-info/licenses/LICENSE.txt
poopmap_api-0.0.2.dist-info/METADATA
poopmap_api-0.0.2.dist-info/WHEEL
poopmap_api-0.0.2.dist-info/top_level.txt
poopmap_api-0.0.2.dist-info/RECORD
