Metadata-Version: 2.4
Name: poopmap-api
Version: 0.0.2
Summary: An unofficial Python client library for the Poop Map API.
Author-email: Lucas van der Horst <Lucas@vdrHorst.nl>
License: MIT
Project-URL: Homepage, https://github.com/Lucas-vdr-Horst/poopmap-api
Project-URL: Issues, https://github.com/Lucas-vdr-Horst/poopmap-api/issues
Keywords: poopmap,api,client,python,wrapper,rest,unofficial,map,social
Classifier: Programming Language :: Python :: 3.10
Classifier: Programming Language :: Python :: 3.11
Classifier: Programming Language :: Python :: 3.12
Classifier: License :: OSI Approved :: MIT License
Classifier: Topic :: Software Development :: Libraries :: Python Modules
Classifier: Intended Audience :: Developers
Classifier: Operating System :: OS Independent
Requires-Python: >=3.10
License-File: LICENSE.txt
Requires-Dist: requests>=2.28.1
Dynamic: license-file
